{
  "metadata": {
    "username": "shuang",
    "fetch_time": "2025-03-28 08:59:49",
    "client_id": "tk-jjLsE5YITku-kQ4raYvZFA",
    "display_name": "Shuang"
  },
  "graph_data": {
    "nodes": [
      {
        "id": "shelf_wishlist",
        "name": "Wishlist",
        "type": "shelf",
        "group": "shelf"
      },
      {
        "id": "shelf_progress",
        "name": "Progress",
        "type": "shelf",
        "group": "shelf"
      },
      {
        "id": "shelf_complete",
        "name": "Complete",
        "type": "shelf",
        "group": "shelf"
      },
      {
        "id": "shelf_dropped",
        "name": "Dropped",
        "type": "shelf",
        "group": "shelf"
      },
      {
        "id": "4LBWky31KfHyNL7u1MKC80",
        "name": "初步举证",
        "type": "movie",
        "shelf": "wishlist",
        "data": {
          "url": "/movie/4LBWky31KfHyNL7u1MKC80",
          "release_date": null,
          "description": "Tessa 是一位年轻有为的刑辩律师，热爱胜利。她从工人阶级出身一步步成长为顶尖律师，在任何案件中都能进行辩护、交叉质证和消除疑点。她不对客户做价值判断，不相信一面之词，甚至不能相信自己的直觉，她只相信“法律下的真相”，法律与系统会做出最接近真相的判决。但一个意外事件迫使她直面父权制下的法律、举证责任和道德之间的分歧。\n在2023英国劳伦斯·奥利弗奖评选中，本剧获得最佳新剧奖，Jodie Comer获得最佳女演员奖。",
          "rating": null,
          "comment": null
        }
      },
      {
        "id": "7Ewenx9aHugGnoOV2DAbs0",
        "name": "粗野派",
        "type": "movie",
        "shelf": "wishlist",
        "data": {
          "url": "/movie/7Ewenx9aHugGnoOV2DAbs0",
          "release_date": null,
          "description": "故事围绕匈牙利出生的犹太建筑师拉斯洛·托斯与妻子埃尔兹贝特展开。他们在二战后逃离欧洲，前往美国重启他们的事业，并见证了现代美国的诞生。然而他们的生活被一名神秘而富有的客户改变了。",
          "rating": null,
          "comment": null
        }
      },
      {
        "id": "1UKRbng4exUWF9VlZlsxR4",
        "name": "猫猫的奇幻漂流",
        "type": "movie",
        "shelf": "wishlist",
        "data": {
          "url": "/movie/1UKRbng4exUWF9VlZlsxR4",
          "release_date": null,
          "description": "世界似乎即将毁灭，到处都是人类的遗迹。一只猫的家园被一场大洪水摧毁，它在一艘载满了不同动物的船上找到了避难所。尽管它们之间存在差异，但它必须与它们合作，面临各种未知的挑战。",
          "rating": null,
          "comment": null
        }
      },
      {
        "id": "35SzNGrMRfQg8ShHu7ypgo",
        "name": "海鸥食堂",
        "type": "movie",
        "shelf": "wishlist",
        "data": {
          "url": "/movie/35SzNGrMRfQg8ShHu7ypgo",
          "release_date": null,
          "description": "芬兰是最接近日本的欧洲国家，坐飞机只需要十个小时。幸惠（小林聪美饰）在风光如画的首都赫尔辛基独自经营一家叫做“海鸥食堂” 的日式餐厅，她希望以简单却温暖的传统手卷留住客人的心，只可惜事与愿违，餐厅经常空无一人。后来，绿（片桐入饰）与正子（罇真佐子饰），因为不同原因，先后来到了那里帮忙。\n再加上日本文化迷的年轻小帅哥顾客，本来只是驻足指点观望，后来却被肉桂卷香味吸引进来的芬兰老太太们，曾在那里工作过而忘不了原来咖啡机的中年男人，认真地询问如何扎稻草人诅咒老公的中年女人。这些有趣而真实的人，围绕在海鸥食堂周围，结下了淡淡的情谊。",
          "rating": null,
          "comment": null
        }
      },
      {
        "id": "670IYdkqOu9ibgRdReKBcz",
        "name": "隔壁房间",
        "type": "movie",
        "shelf": "wishlist",
        "data": {
          "url": "/movie/670IYdkqOu9ibgRdReKBcz",
          "release_date": null,
          "description": "英格丽（朱丽安·摩尔 Julianne Moore 饰）和玛莎（蒂尔达·斯文顿 Tilda Swinton 饰）年轻时是好朋友，她们曾在同一家杂志社工作。后来英格丽成为了一名小说家，而玛莎成为了一名战地记者，她们渐行渐远。失联多年后，她们重新开始了联系。",
          "rating": null,
          "comment": null
        }
      },
      {
        "id": "7DG7zq17uYyKPaXA3XTOtc",
        "name": "借东西的小人阿莉埃蒂",
        "type": "movie",
        "shelf": "wishlist",
        "data": {
          "url": "/movie/7DG7zq17uYyKPaXA3XTOtc",
          "release_date": null,
          "description": "虽然患有心脏方面的疾病，但是少年翔（神木隆之介 配音）的父母依然对他疏于呵护。为了准备即将到来的手术，翔来到了位于偏远乡间的姨婆（竹下景子 配音）家静养。姨婆家位于一片幽静的丛林中，这是一幢有着上百年历史的欧式别墅。这里除了生活着姨婆和女佣阿春（树木希林 配音）外，还有一个奇特的三口之家，“借东西一族”——小人阿莉埃蒂（志田未来 配音）和她的爸爸（三浦友和 配音）妈妈（大竹忍 配音），他们生活在别墅的地板下，只有几公分高，过着不为人类察觉的生活。遇到所需的日常用品时，便会在夜深人静之时偷偷潜入厨房借出来。翔无意中瞥见阿莉埃蒂的身影，他有心接近这些传说中的小人，却不知不觉打扰了他们的生活…… 本片根据英国作家玛丽·诺顿的原著《借东西的小人》改编，并荣获2011年日本电影学院奖最佳动画片奖。",
          "rating": null,
          "comment": null
        }
      },
      {
        "id": "2WviyrRefSmAVlFZ825eAQ",
        "name": "玛莎·斯图尔特自传",
        "type": "movie",
        "shelf": "wishlist",
        "data": {
          "url": "/movie/2WviyrRefSmAVlFZ825eAQ",
          "release_date": null,
          "description": "这是一部关于玛莎·斯图尔特的权威纪录片，包含了一系列与这位偶像本人的坦诚访谈。从她在华尔街的早期起步到成为最早的网红，斯图尔特在每个十年中不断重塑自己。",
          "rating": null,
          "comment": null
        }
      },
      {
        "id": "3uPZ9v0yM6AKLIJh8QfmEK",
        "name": "钢琴课",
        "type": "movie",
        "shelf": "wishlist",
        "data": {
          "url": "/movie/3uPZ9v0yM6AKLIJh8QfmEK",
          "release_date": null,
          "description": "苏格兰单身母亲艾达·麦格拉斯（霍利·亨特 饰）自六岁起就放弃了讲话，只通过钢琴倾诉满腔情感。1852年，麦格拉斯远嫁新西兰的斯图尔特（山姆·尼尔 饰），将钢琴也一并带了去。可是斯图尔特人手不够，只得将笨重的钢琴遗弃海滩。斯图尔特之友乔治·贝恩斯（哈维·凯特尔 饰）爱上了麦格拉斯，用八十英亩土地与斯图尔特交易。斯图尔特转让了钢琴，并命麦格拉斯教贝恩斯奏琴。钢琴课上，贝恩斯提议，如果麦格拉斯在教琴的时候允许某些出格的事情发生，一次课便可换回一个琴键……",
          "rating": null,
          "comment": null
        }
      },
      {
        "id": "2VG91G8xAAkbJRBtEncPcN",
        "name": "镜子",
        "type": "movie",
        "shelf": "wishlist",
        "data": {
          "url": "/movie/2VG91G8xAAkbJRBtEncPcN",
          "release_date": null,
          "description": "本片是导演安德烈·塔科夫斯基（Andrei Tarkovsky）的一部自传体电影。幼年的塔科夫斯基随着母亲（玛格瑞塔·泰瑞柯娃 Margarita Terekhova 饰）去亲戚家借钱，他独自在一个陌生的房间里发现了一面镜子，并通过镜子审视自己，在巴赫的音乐中，塔可夫斯基的回忆慢慢带出了一系列的事件：电视上在播报一个口吃的年轻人通过催眠治痊了自己；一个被家庭忽视的妻子遇上一位迷路的乡村医生，两人之间产生若即若离的关系；一个未曾露面的叙述者与前妻在争吵；一个早熟的年轻人备受军事指导员的呵责。这些毫无关联的片段式回忆通过镜子串联起来，展现了导演对时间、历史、生活、土地、梦境等意象的哲学思考。\n导演的母亲在影片中扮演艺术家的母亲；他的父亲，一位著名的俄罗斯诗人，在画外音中朗读自己的诗作。",
          "rating": null,
          "comment": null
        }
      },
      {
        "id": "4yC7xKuvHEdBN6m8nXjz6f",
        "name": "乡愁",
        "type": "movie",
        "shelf": "wishlist",
        "data": {
          "url": "/movie/4yC7xKuvHEdBN6m8nXjz6f",
          "release_date": null,
          "description": "俄国诗人安德烈（奥列格·扬科夫斯基 Oleg Yankovsky 饰）在美丽的女翻译尤金伲亚（多美兹亚娜·佐丹奴 Domiziana Giordano 饰）的陪同下，一同前往意大利寻访一位十八世纪俄国作曲家的生活。他们一起走访充满宗教意象的乡村教堂，在一座有天然温泉的古老小镇停留。 此时他遇见了不被世人理解的疯人多米尼克（厄兰·约瑟夫森 Erland Josephson 饰），村民因为他早些年囚禁家人而认为他神经失常。可安德烈看到了多米尼克疯狂下的深意，并被他所吸引。同时他拒绝了性感的尤金伲亚的示爱。此时的安德烈，游走在支离破碎的现实与超现实的梦境中不能自拔。他对祖国的思念、与家人的分离……种种情愫混杂在一起，彼此纠缠，化为终生的乡愁。\n本片获1983年戛纳电影节最佳导演奖，普通评审团奖，国际影评人费比西奖。",
          "rating": null,
          "comment": null
        }
      },
      {
        "id": "0fwcTqyqG5V2XjC4ZsAVuP",
        "name": "飞向太空",
        "type": "movie",
        "shelf": "wishlist",
        "data": {
          "url": "/movie/0fwcTqyqG5V2XjC4ZsAVuP",
          "release_date": null,
          "description": "心理学家克里斯•凯尔文（Donatas Banionis 饰）在飞往索拉瑞斯星之前来到儿时的父母家与当年的索拉瑞斯飞行员亨利•伯顿（Vladislav Dvorzhetsky 饰）见面。伯顿警告凯尔文索拉瑞斯星上会有不可思议的奇事发生，但后者并不以为意。凯尔文离开前，当 着父亲（尼古莱•格陵柯Nikolai Grinko 饰）的面焚毁了自己的个人物品。凯尔文到达索拉瑞斯星附近的太空站后，对科学家奇巴瑞安博士（Sos Sargsyan 饰）之死进行调查，却发现自己多年前已经去世的妻子哈莉（Natalya Bondarchuk 饰）竟突然出现。惊慌失措的凯尔文与太空站上另三位科学家讨论该如何面对怪事，却发现原来每人都深受其扰，不明就里……\n本片被提名1972年戛纳电影节金棕榈奖，并获同年戛纳电影节评委会大奖和国际影评人协会大奖。",
          "rating": null,
          "comment": null
        }
      },
      {
        "id": "3me8ZM9sgWnIcG4583NKeJ",
        "name": "旺达",
        "type": "movie",
        "shelf": "wishlist",
        "data": {
          "url": "/movie/3me8ZM9sgWnIcG4583NKeJ",
          "release_date": null,
          "description": "　　住在宾夕法尼亚矿区的旺达潦倒落魄。她偶尔工作，抛弃了丈夫和孩子，睡在她姐姐的沙发上，抽烟喝酒，然后和男人一起回家，只为了能有一个地方安身。一天晚上，她走进酒吧后发现丹尼斯有点紧张。她和他交往，确认他是个罪犯。丹尼斯正计划着抢劫。尽管他粗鲁无礼，旺达却欣然接受了他的虐待。",
          "rating": null,
          "comment": null
        }
      },
      {
        "id": "3UXPmGxYF8YelJlDj3ZW0L",
        "name": "修罗雪姬",
        "type": "movie",
        "shelf": "wishlist",
        "data": {
          "url": "/movie/3UXPmGxYF8YelJlDj3ZW0L",
          "release_date": null,
          "description": "德川幕府倒台，日本进入开明的民主时代。但是明治时期政府、军队及至商贾仍存在腐败贪婪的现象。明治八年爆发血税暴乱，小学教师鹿岛刚（大門正明 饰）携家眷旅行途中遭到暴乱农民的袭击，鹿岛和儿子司郎（内田慎一 饰）惨遭杀害，他的妻子小夜（赤座美代子 饰）则被暴民侵犯。在此之后，小夜瞅准时机杀死一名暴徒，入狱后她与狱警、官员私通，千方百计产下一女，取名雪姬，并将为家族复仇的使命交给女儿。狱友同情小夜的遭遇，想尽办法将雪姬托付给武功高强的僧人大臣道海（西村晃 饰）修行。20年后，背负着莫大仇恨的修罗雪姬（梶芽衣子 饰）携着血雨腥风来至人间……\n本片根据小池一夫（漫画脚本）和上村一夫（作画）的漫画原著改编，主题歌后被昆汀·塔伦蒂诺用到《杀死比尔》中。",
          "rating": null,
          "comment": null
        }
      },
      {
        "id": "0CobfxIjswfZZJltBSL6SJ",
        "name": "林璎：强烈而清晰的洞察力",
        "type": "movie",
        "shelf": "wishlist",
        "data": {
          "url": "/movie/0CobfxIjswfZZJltBSL6SJ",
          "release_date": null,
          "description": "林璎(Maya Ying Lin)美籍华裔建筑大师，林徽因的侄女。作品遍布美国各地，曾入选美国《生活》杂志评选的“20世纪最重要的100位美国人”与“50位美国未来的领袖”。今年，美国总统奥巴马在白宫为她颁发2009年度美国国家艺术奖章，表彰她作为建筑师、艺术家环保人士的卓著成就，这是美国官方给予艺术家的最高荣誉。zx.findart.com.cn\n“我的作品，来源于一种使人们能够认识他们所生存环境的单纯愿望。这种环境既包括他们物质上的，也包括他们心理上的生存环境。”\n1987年，美籍华裔建筑师林璎，成为耶鲁大学有史以来最年轻的博士。毕业典礼上，她以“艺术与社会的密切关系”为题，作了一场精彩演讲。\n“我们每个人都是整体意识的一部分，通过我们的作品、形象、思想、写作等等而彼此关联。我们将在这些沟通中告诉未来的一代，我们是谁、曾经做过什么，可能的话，还包括我们将对他们产生什么样的正面影响。”zx.findart.com.cn\n早在21岁时，林璎就因设计越战纪念碑一夜成名。从战争到民权，从女权到种族平等，针对美国的历史性议题，她又先后创作了“民权运动纪念碑”、耶鲁“妇女之桌”，以及为纪念美洲印第安原住民创作的7件雕塑装置组合“汇流”。zx.findart.com.cn\n这些声名赫赫的纪念碑都是应邀之作，“但是我愿意创作最后一座纪念碑，它集中体现了我成长时期乃至今天仍是最重要的问题：环境以及人类同环境的关系”。",
          "rating": null,
          "comment": null
        }
      },
      {
        "id": "1KM91zYKjGdciZawXrCl1h",
        "name": "梦",
        "type": "movie",
        "shelf": "wishlist",
        "data": {
          "url": "/movie/1KM91zYKjGdciZawXrCl1h",
          "release_date": null,
          "description": "本片是日本电影天皇黑泽明对梦的勾画，全片共有八个梦境，分别是：太阳雨、桃园、风雪、隧道、乌鸦、红色富士山、垂泪的魔鬼和水车之村。这八个梦几乎贯穿了人类生活的所有主题，战争与和平、社会与人生。在不同的梦境里有着不同的场景，配合不同的色彩，把人类所面对的所有主题一一呈现。",
          "rating": null,
          "comment": null
        }
      },
      {
        "id": "3t2X3K2gL3ryF84lFQE0u4",
        "name": "侧耳倾听",
        "type": "movie",
        "shelf": "wishlist",
        "data": {
          "url": "/movie/3t2X3K2gL3ryF84lFQE0u4",
          "release_date": null,
          "description": "正在读初三的月岛雯是一个喜欢看书的女孩，她每次都能在借书卡上看到一个叫天泽圣司名字，因此她对这个人充满了好奇。 雯一直喜欢写诗，有一天她跟好友夕子在讨论写诗的事，夕子告诉雯自己收到了情书，但事实上夕子已有了喜欢的人。更没有想到的是，夕子喜欢的杉村喜欢的是雯，雯一时间感到十分困惑。 雯无意中来到了一个小店，原来店主是圣司的爷爷。认识了圣司之后，听到了圣司对自己理想的追求之后，也激发了雯对自己理想的追求之念。当圣司离开了到意大利学习做小提琴时，雯决定要专心写作。当雯完成了作品之后，她发现原来自己高估了自己，就这样她选择继续考高中，这时她非常想念圣司。 一天凌晨，她站到窗边，突然看到了一个熟悉的身影……",
          "rating": null,
          "comment": null
        }
      },
      {
        "id": "4NQC4sGwaR5jiqhGiRRLtP",
        "name": "寻找小糖人",
        "type": "movie",
        "shelf": "wishlist",
        "data": {
          "url": "/movie/4NQC4sGwaR5jiqhGiRRLtP",
          "release_date": null,
          "description": "罗德里格斯在上世纪70年代发行过两张专辑《Cold Fact》与《Coming From Reality》，在南非有超过50万的销量且知名度可与滚石乐队相提并论。但与其他知名的美国歌手不同，南非的歌迷得不到任何一点关于罗德里格斯的信息，除了专辑歌曲之外唯一能了解的只有专 辑封面上一张并不清晰的相片。两张专辑后，他好像也就此销声匿迹。\n对于在南非的辉煌成绩，罗德里格斯其实并不知情，他在美国过着截然不同的生活，没有知名度，专辑销量不佳，被唱片公司抛弃，曾经一度做着装修屋顶的体力活…… 南非开普敦一家唱片店老板斯蒂芬与音乐记者克雷格听到罗德里格斯在舞台上奇特自杀的传闻后展开调查，寻找小糖人之路就此开始，一段神秘的传奇故事就此展开……",
          "rating": null,
          "comment": null
        }
      },
      {
        "id": "4fr1rDv2291dAVKPtcMRgP",
        "name": "失乐园",
        "type": "movie",
        "shelf": "wishlist",
        "data": {
          "url": "/movie/4fr1rDv2291dAVKPtcMRgP",
          "release_date": null,
          "description": "久木祥一郎（役所广司饰）是一家出版社的高级编辑，妻子久木文枝（星野知子饰）做设计陶制品，已成年的女儿在医院工作，很少回家。祥一朗感到家庭生活乏味，夫妻间总是客客气气。 祥一郎有个情人，业余书法教师松原凛子（黑木瞳饰）。凛子气质高雅，是个聪慧女子。可惜嫁了个毫无情趣的医生丈夫松原晴彦。他冷冰冰的，导致二人婚姻空虚。一次他坚决地告诉凛子决不会和她离婚，他掌握有妻子偷情的证据，并揭发了事情。另一边文枝却默默承受，最终也只能离婚。冬季到来，祥一郎和凛子怎么才能永远的和对方长相厮守呢？",
          "rating": null,
          "comment": null
        }
      },
      {
        "id": "5MRX5FqPV4gQJ4SUJEGR6y",
        "name": "其后",
        "type": "movie",
        "shelf": "wishlist",
        "data": {
          "url": "/movie/5MRX5FqPV4gQJ4SUJEGR6y",
          "release_date": null,
          "description": "20世纪初的日本，毕业于东京帝国大学的长井代助（松田优作 饰）家境优渥，全然不曾为金钱烦恼。他终日周游玩乐，过着悠闲自在的高等无业游民的生活。与之相对，和长井相交多年的好友平冈常次郎（小林薰 饰）生活拮据，妻子三千代（藤谷美和子 饰）孕期患上心脏病，未出生的孩子更不幸夭折。承受巨大压力的平冈破罐破摔，流连烟花场所。生计日益紧迫的同时，夫妻情分名存实亡。三千代是长井、平冈大学时代亡友菅沼（风间杜夫 饰）的妹妹，此去经年，始终未婚的长井依然对三千代持有深深的爱慕，他同情对方的境遇，但碍于道德的束缚只能将炽烈的情感深锁心底。深爱无缘，百千心结何处搁置……\n本片根据夏目漱石的同名原作改编。",
          "rating": null,
          "comment": null
        }
      },
      {
        "id": "18pFJWDeqhqBh48Sxwnw63",
        "name": "海上花",
        "type": "movie",
        "shelf": "wishlist",
        "data": {
          "url": "/movie/18pFJWDeqhqBh48Sxwnw63",
          "release_date": null,
          "description": "上海英租界里，高级妓院被称为“长三公寓”。长三公寓里的红倌人沈小红（羽田美智子 饰）、黄翠凤（李嘉欣 饰）与周双珠（刘嘉玲 饰）心事迥异。一个想同某个男人建立长久关系，一个在与多个男人斡旋时已秘密锁定其中最有闲有钱的一位，想其将来帮她赎身，另一个心地仁厚，却又看破红尘，觉得人生不过如此……\n该片改编自张爱玲曾将其“注译”成国语的吴语小说《海上花列传》。",
          "rating": null,
          "comment": null
        }
      },
      {
        "id": "3ErINWu9y8qqJzA3uSJxaK",
        "name": "幽灵公主",
        "type": "movie",
        "shelf": "complete",
        "data": {
          "url": "/movie/3ErINWu9y8qqJzA3uSJxaK",
          "release_date": null,
          "description": "为了拯救危难中的村民，阿斯达卡的右手中了凶煞神的诅咒。达卡只好离开亲人往西方流浪以寻找解除诅咒的方法。旅途中他遇到了由幻姬大人带领的穷苦村民在麒麟兽的森林里开采铁矿，提炼矿石。 白狼神莫娜和她养大的人类女孩“幽灵公主”桑对幻姬恨之入骨，因为她们觉得幻姬带领众人破坏了森林。想帮助人类的阿斯达卡被桑深深吸引，他理解她，但为了帮助穷人又不得不和她作战。一次战斗中，阿斯达卡被麒麟兽所救，他的立场更加摇摆不定。 这时，以疙瘩和尚为首的一群人来杀麒麟兽，幻姬以火枪击毙了麒麟，麒麟的头被疙瘩和尚抢走。愤怒的麒麟的灵魂为夺回自己的头，大肆破坏着森林。阿斯达卡和桑联手决定帮麒麟夺回头颅。",
          "rating": null,
          "comment": null
        }
      },
      {
        "id": "1GJZfHPBtJf3ekmbeA90Ts",
        "name": "编舟记",
        "type": "movie",
        "shelf": "complete",
        "data": {
          "url": "/movie/1GJZfHPBtJf3ekmbeA90Ts",
          "release_date": null,
          "description": "玄武书房拟定出版一部面向当代人的中型国语辞典《大渡海》，阅历颇丰且行事一丝不苟的国语学者松本朋佑（加藤刚 饰）作为监修主持工作，谁知他最为器重的编辑荒木公平（小林薰 饰）却到了退休的年龄，选择回家照顾病中的妻子。此时编辑部中仅有做事浮躁的西冈正志（小田切让 饰）和临时工佐佐木熏（伊佐山博子 饰）。荒木和西冈多方物色，终于相中了营业部内不善于和人交往却对词语有着敏锐认知度以及做事极为认真投入的青年马缔光也（松田龙平 饰）。浩瀚的词语海洋，马缔与同事们用长达十五年的时间编制一艘驶向彼岸的小船。他们甘于寂寞，却也收获着弥足珍贵的幸福……\n本片根据三浦紫苑的同名原作改编。",
          "rating": null,
          "comment": null
        }
      },
      {
        "id": "1MQTe6StK7U9anZfXwrvxN",
        "name": "姥姥的外孙",
        "type": "movie",
        "shelf": "complete",
        "data": {
          "url": "/movie/1MQTe6StK7U9anZfXwrvxN",
          "release_date": null,
          "description": "M出生于一个华侨家族中，20多岁的他还没找到正经工作，只得在家中做一个名不见经传的游戏主播。一次偶然姥姥检查出身患癌症，只有一年可活。这让M动了继承姥姥房产的心思。他找到独居的姥姥想要照顾姥姥最后的时光。在接下来的时间里，M也算尽心尽力，慢慢地他发现，姥姥其实是十分孤独的。虽然有三个儿女却不经常回来看她，大儿子只顾着自己的家庭，小儿子还因为赌博负债累累。因为不想连累子女什么事都自己忍着。她全心全意地爱着自己的没一个孩子却没有收到同等的回报。渐渐地，M不再将房子作为自己的目的，他是真心想要陪伴姥姥这最后的时光。姥姥的病情逐渐严重，她看到负债的小儿子便把房子给了小儿子。M十分生气，他只是觉得姥姥将自己的爱错付，因为小儿子根本不领情。可当看到虚弱的姥姥躺在养老院，他却觉得一切都不重要，只要还能陪伴她。好景不长，姥姥去世了。M收到银行的电话通知他姥姥为他存了一大笔钱。这是在M小的时候姥姥就准备的，这么多年靠她自己卖粥积攒下来的。这时，M才明白，原来姥姥的爱是如此深沉，也让他明白亲情的重要。",
          "rating": null,
          "comment": null
        }
      },
      {
        "id": "5SfUpBL7Ep6RIIa7TQBmtT",
        "name": "何以为家",
        "type": "movie",
        "shelf": "complete",
        "data": {
          "url": "/movie/5SfUpBL7Ep6RIIa7TQBmtT",
          "release_date": null,
          "description": "法庭上，十二岁的男孩赞恩向法官状告他的亲生父母，原因是，他们给了他生命。是什么样的经历让一个孩子做出如此不可思议的举动？故事中，赞恩的父母在无力抚养和教育的状况下依然不停生育，作为家中的长子赞恩，弱小的肩膀承担了无数生活的重压。当妹妹被强行卖给商贩为妻时，赞恩愤怒离家，之后遇到一对没有合法身份的母子，相互扶持勉强生活。然而生活并没有眷顾赞恩，重重磨难迫使他做出了令人震惊的举动……",
          "rating": null,
          "comment": null
        }
      },
      {
        "id": "6SypDUBDZDeKkHSHfWRILc",
        "name": "走走停停",
        "type": "movie",
        "shelf": "complete",
        "data": {
          "url": "/movie/6SypDUBDZDeKkHSHfWRILc",
          "release_date": null,
          "description": "脆皮青年吴迪（胡歌 饰），工作感情双双失意，沮丧返乡。吴迪“突袭”返乡的行为打破了一家人原本平静的生活，他不仅需要重新面对与家人的“亲密”相处，还要为自己的未来寻找更多的可能。在现实面前多番碰壁后，一次偶然的机会下他与高中同学冯柳柳（高圆圆 饰）相遇，随后生活也发生了意想不到的转变。",
          "rating": null,
          "comment": null
        }
      },
      {
        "id": "59TkmZ7Evnn4xGWSY7fkgo",
        "name": "朝云暮雨",
        "type": "movie",
        "shelf": "complete",
        "data": {
          "url": "/movie/59TkmZ7Evnn4xGWSY7fkgo",
          "release_date": null,
          "description": "影片改编自真实故事《穿婚纱的杀人少女》。刑满释放人员老秦（范伟 饰）服刑27年后出狱，只想娶妻生子，开启新的人生，却意外结识同样刚出狱的女孩常娟（周冬雨 饰）。他求子，她求财，“同是天涯沦落人”的两人开始了一段各怀目的的利益婚姻。",
          "rating": null,
          "comment": null
        }
      },
      {
        "id": "5ZQLUcgq9hI0ZRq4DnJ9Nw",
        "name": "原始星球",
        "type": "movie",
        "shelf": "complete",
        "data": {
          "url": "/movie/5ZQLUcgq9hI0ZRq4DnJ9Nw",
          "release_date": null,
          "description": "茫茫宇宙中一颗无名星球上，生活着体形悬殊的两种生物。占主导地位的是戴格斯人，他们身形巨大，拥有极高的文明和智慧，可以使精神摆脱肉体自在游弋；与之相对的是奥姆斯人，他们具有地球人的外表和身形，社会形态原始落后，在戴格斯人面前有如蝼蚁，于是当仁不让成为这些巨人的奴隶和玩物。奥姆斯人具有顽强的生命力和繁殖能力，他们的数量与日俱增，造成了统治者的困扰。于是，一场针对奥姆斯人的剿灭战随即展开。这本是一场微不足道的如同剿灭害虫的行动，但一个不起眼的奥姆斯人改变了双方的格局。泰尔是被一个戴格斯女孩豢养的奥姆斯男性宠物，他通过主人的教学机器学到了戴格斯人先进的科学文化知识。偶然机会，泰尔逃离戴格斯家庭，成为了领导奥姆斯人对抗统治者的领袖……\n本片荣获1973年戛纳电影节特别奖。",
          "rating": null,
          "comment": null
        }
      },
      {
        "id": "7SReOVIEq3itRypnDbcRqE",
        "name": "你想活出怎样的人生",
        "type": "movie",
        "shelf": "complete",
        "data": {
          "url": "/movie/7SReOVIEq3itRypnDbcRqE",
          "release_date": null,
          "description": "少年牧真人（山时聪真 配音）的母亲葬身火海后，他随父亲牧胜一（木村拓哉 配音）与继母夏子（木村佳乃 配音）组成新家庭。深陷悲伤的真人阴郁孤僻，难以融入新环境。一次意外，他跟随一只会说话的苍鹭（菅田将晖 配音）闯入废弃的神秘塔楼，却不料进入了奇幻的“亡灵世界”，开始了一场不可思议的冒险……\n影片片名致敬了小说家吉野源三郎在1937年发表的同名小说，但电影故事由宫崎骏原创。",
          "rating": null,
          "comment": null
        }
      },
      {
        "id": "6O7xHFAeXj8lmvsUJhpsIm",
        "name": "崖上的波妞",
        "type": "movie",
        "shelf": "complete",
        "data": {
          "url": "/movie/6O7xHFAeXj8lmvsUJhpsIm",
          "release_date": null,
          "description": "海神的女儿波妞从深海出逃玩耍，却被困在玻璃瓶里冲到岸上，碰巧被住在岸边悬崖的宗介救出，两人因此相识。但是波妞的父亲——魔法师藤本，认为人类世界肮脏丑陋，强行把波妞带回海里。面对父亲的阻挠、席卷小镇的海啸，以及永远失去魔法的威胁，波妞仍然大胆而坚决地决定——要变成人类跟宗介在一起。而承诺要永远保护波妞的宗介，也即将面临新的挑战。",
          "rating": null,
          "comment": null
        }
      },
      {
        "id": "3aUNnyrU6XNSjKp3mHIUGy",
        "name": "特工",
        "type": "movie",
        "shelf": "complete",
        "data": {
          "url": "/movie/3aUNnyrU6XNSjKp3mHIUGy",
          "release_date": null,
          "description": "1990年代中期，暗号「黑金星」的南韩「国家安全企划部」情报员，假扮成南韩商人跟北韩进行商业交易，藉此渗透北韩军事单位，打探核开发情报，他得在最危险的地方，赢得敌方的信任，没想到一心只想完成任务的他，却在不自觉中陷入南北韩权力高层间的恐怖阴谋。",
          "rating": null,
          "comment": null
        }
      },
      {
        "id": "0rlhTdTgCiMzTsk6Nzc1qO",
        "name": "自梳",
        "type": "movie",
        "shelf": "complete",
        "data": {
          "url": "/movie/0rlhTdTgCiMzTsk6Nzc1qO",
          "release_date": null,
          "description": "一段穿越50年时空的真情。两个女人的苦难与爱恨，让人心碎却也心醉。现代女性阿慧（李绮虹饰）从美国学习建筑业归来，在香港与大陆间经营事业，是个新时代的女强人。其男友（赵文煊饰）也是其下属，二人感情渐淡，男友移情别恋。阿慧伤心却也无奈。阿慧父亲委托阿慧陪其幼年时的奶妈欢姑（归亚蕾饰）回乡探旧友，两人一见面就针锋相对，相处不太愉快。随着旅程的进行，二人矛盾不断，却也渐渐磨合。欢姑在开导感情脆弱的阿慧时，道出了一段隐藏在心底的往事。 40年代的广东顺德，女子还生活在男权制的枷锁下。年轻的意欢（杨采妮饰）被父亲卖于地主，她宁愿做自梳女，宁死不从。被途经路过的杏花楼妓女玉环（刘嘉玲饰）救下。玉环嫁给了当地织布厂厂主陈耀宗（董玮饰）做了八姨太，与其他太太明争暗斗不断，却将意欢认为知己，二人无话不谈。意欢与青梅竹马的恋人（钱嘉乐饰）两情相悦却难成眷属。玉环被丈夫出卖，成为军阀谈生意的筹码，愤怒之下，她离开了陈家。意欢对玉环不离不弃，令她十分感动，感情渐渐超越了友谊。而此时意欢与恋人在“买门槛”之夜出轨，玉环又担心又生气，终于忍不住告诉了意欢自己心底的秘密。有情人能否终成眷属？两个女人之间到底有什么秘密？阿慧能否度过情关？而欢姑苦苦寻找了50年的人又是谁？ 《自梳》是大导演张之亮的名作，朴实无华却感人肺腑，人性刻画深刻，对时代的敏感度也可见一二，是国产女同电影的最佳之作。",
          "rating": null,
          "comment": null
        }
      },
      {
        "id": "61VXoCBbwZmEPMpek3dPv5",
        "name": "周处除三害",
        "type": "movie",
        "shelf": "complete",
        "data": {
          "url": "/movie/61VXoCBbwZmEPMpek3dPv5",
          "release_date": null,
          "description": "通缉犯陈桂林（阮经天 饰）生命将尽，却发现自己在通缉榜上只排名第三，他决心查出前两名通缉犯的下落，并将他们一一除掉。陈桂林以为自己已经实现了当代的周处除三害，却没想到永远参不透的贪嗔痴，才是人生终要面对的罪与罚。",
          "rating": null,
          "comment": null
        }
      },
      {
        "id": "7W8mWPRsHRbscXIKDwaDNt",
        "name": "宠爱",
        "type": "movie",
        "shelf": "complete",
        "data": {
          "url": "/movie/7W8mWPRsHRbscXIKDwaDNt",
          "release_date": null,
          "description": "讲述民相与养狗的珍英个性不合。敏瑞是知名的建筑师，需要敏瑞帮助的民相，瞄准了珍英和她的狗。某天，敏瑞昏倒在路上，狗狗万达也走失。敏瑞与振宇一起寻找万达。另一边，贤正照顾着女友的狗，但女友的前男友丹尼尔却突然出现。与毛茸茸的朋友们交织在一起的他们，将展开一段令人愉悦的故事！",
          "rating": null,
          "comment": null
        }
      },
      {
        "id": "0CcoCzEy5UsdunAqMezUK1",
        "name": "青春变形记",
        "type": "movie",
        "shelf": "complete",
        "data": {
          "url": "/movie/0CcoCzEy5UsdunAqMezUK1",
          "release_date": null,
          "description": "[包宝宝]导演石之予将执导迪士尼·皮克斯动画长片[变红](Turning Red，暂译)。该片讲述少女Mei在兴奋的时候会变成一只巨大的红色小熊猫。该片将于2022年3月11日北美上映。",
          "rating": null,
          "comment": null
        }
      },
      {
        "id": "1tx0NXYNYw1B1EbzEOH8Ut",
        "name": "破墓",
        "type": "movie",
        "shelf": "complete",
        "data": {
          "url": "/movie/1tx0NXYNYw1B1EbzEOH8Ut",
          "release_date": null,
          "description": "影片讲述接受巨额资金委托移葬可疑墓地的风水师和同行的葬仪师、巫女之间发生的奇异事件。",
          "rating": null,
          "comment": null
        }
      },
      {
        "id": "50UegkSltjhfK9xvcVRPfJ",
        "name": "画江湖之不良帅",
        "type": "movie",
        "shelf": "complete",
        "data": {
          "url": "/movie/50UegkSltjhfK9xvcVRPfJ",
          "release_date": null,
          "description": "袁天罡，天生弃命格，客死家人后来到藏兵谷投奔叔叔。他15岁之际，天下大乱，负责守护龙渊剑的藏兵谷惨遭地煞们血洗，他再睁眼只见满山坟冢。从此以后，他决定与命一博，习得称骨算命之术，成为杀手且专杀命不该绝之人。35岁那年，在西北边陲的小镇上结识了买凶杀人的客栈老板娘幻音。幻音刺杀李渊寡不敌众，袁天罡前来营救时遇见了旧时故人李淳风。从此，龙渊再现江湖，袁天罡守护者的身份也公诸于世。是肩挑守护王朝的责任，还是归于江湖做行侠仗义的行者？不良帅的故事正在上演......",
          "rating": null,
          "comment": null
        }
      },
      {
        "id": "73OfKaiBtVf3Z2zTl2UVlH",
        "name": "眩：北斋之女",
        "type": "movie",
        "shelf": "complete",
        "data": {
          "url": "/movie/73OfKaiBtVf3Z2zTl2UVlH",
          "release_date": null,
          "description": "葛饰北斋的三女阿荣离婚后回到北斋身边生活，在研习画技的同时望着父亲的背影开始研究色彩与光影，试图寻找自己的艺术之路。而阿荣的母亲则开始惦记让阿荣暗恋的画家善次郎入赘到家里来，但是没想到北斋忽然中风了，阿荣也不得不暂时放下画笔照顾起北斋的生活。放下画笔这段时间，对艺术创新困惑了许久的阿荣好像有了新的感悟……",
          "rating": null,
          "comment": null
        }
      },
      {
        "id": "4S7NSuBKA3bpAjDbxXmxr3",
        "name": "慕尼黑：战争边缘",
        "type": "movie",
        "shelf": "complete",
        "data": {
          "url": "/movie/4S7NSuBKA3bpAjDbxXmxr3",
          "release_date": null,
          "description": "1938 年秋天，欧洲处于战争的边缘。阿道夫·希特勒正准备入侵捷克斯洛伐克，内维尔·张伯伦政府拼命寻求和平解决方案。随着压力的增加，英国官员休·莱加特和德国外交官保罗·冯·哈特曼前往慕尼黑参加紧急会议。谈判的开始后，这两位老朋友发现自己处于政治诡计的中心，同时面临非常现实的危险。\r\n改编自罗伯特哈里斯同名小说。",
          "rating": null,
          "comment": null
        }
      },
      {
        "id": "0vkg5uKj3fNYCREftjzvi2",
        "name": "巴斯特·斯克鲁格斯的歌谣",
        "type": "movie",
        "shelf": "complete",
        "data": {
          "url": "/movie/0vkg5uKj3fNYCREftjzvi2",
          "release_date": null,
          "description": "《巴斯特·斯克鲁格斯的歌谣》是由六个部分组成的西部题材选集电影，乔尔·科恩和伊桑·科恩利用他们独树一帜又无与伦比的视角，讲述了关于美国边境的系列故事。电影的每一章都讲述了一则独特的美国西部故事。",
          "rating": null,
          "comment": null
        }
      },
      {
        "id": "59HnjEbpyVtxmZT3pfNaOm",
        "name": "爱情神话",
        "type": "movie",
        "shelf": "complete",
        "data": {
          "url": "/movie/59HnjEbpyVtxmZT3pfNaOm",
          "release_date": null,
          "description": "李小姐（马伊琍 饰），带着女儿过着单身生活。蓓蓓（吴越 饰），离婚后热衷跳探戈。格洛瑞亚（倪虹洁 饰），有钱有闲老公失踪。三个完全不同的女人因为老白（徐峥 饰）而产生了交集。上海爷叔老白自称杂家，专门教老年人画画。老白的好友老乌谈吐风趣，一生追逐浪漫。几顿饭局，让老白家的客厅成为了众人的聚会点。三女两男，在上海这座摩登之都里，凭借智慧、幽默过招，描摹出多样的市井烟火。",
          "rating": null,
          "comment": null
        }
      }
    ],
    "links": [
      {
        "source": "shelf_wishlist",
        "target": "4LBWky31KfHyNL7u1MKC80",
        "type": "contains"
      },
      {
        "source": "shelf_wishlist",
        "target": "7Ewenx9aHugGnoOV2DAbs0",
        "type": "contains"
      },
      {
        "source": "shelf_wishlist",
        "target": "1UKRbng4exUWF9VlZlsxR4",
        "type": "contains"
      },
      {
        "source": "shelf_wishlist",
        "target": "35SzNGrMRfQg8ShHu7ypgo",
        "type": "contains"
      },
      {
        "source": "shelf_wishlist",
        "target": "670IYdkqOu9ibgRdReKBcz",
        "type": "contains"
      },
      {
        "source": "shelf_wishlist",
        "target": "7DG7zq17uYyKPaXA3XTOtc",
        "type": "contains"
      },
      {
        "source": "shelf_wishlist",
        "target": "2WviyrRefSmAVlFZ825eAQ",
        "type": "contains"
      },
      {
        "source": "shelf_wishlist",
        "target": "3uPZ9v0yM6AKLIJh8QfmEK",
        "type": "contains"
      },
      {
        "source": "shelf_wishlist",
        "target": "2VG91G8xAAkbJRBtEncPcN",
        "type": "contains"
      },
      {
        "source": "shelf_wishlist",
        "target": "4yC7xKuvHEdBN6m8nXjz6f",
        "type": "contains"
      },
      {
        "source": "shelf_wishlist",
        "target": "0fwcTqyqG5V2XjC4ZsAVuP",
        "type": "contains"
      },
      {
        "source": "shelf_wishlist",
        "target": "3me8ZM9sgWnIcG4583NKeJ",
        "type": "contains"
      },
      {
        "source": "shelf_wishlist",
        "target": "3UXPmGxYF8YelJlDj3ZW0L",
        "type": "contains"
      },
      {
        "source": "shelf_wishlist",
        "target": "0CobfxIjswfZZJltBSL6SJ",
        "type": "contains"
      },
      {
        "source": "shelf_wishlist",
        "target": "1KM91zYKjGdciZawXrCl1h",
        "type": "contains"
      },
      {
        "source": "shelf_wishlist",
        "target": "3t2X3K2gL3ryF84lFQE0u4",
        "type": "contains"
      },
      {
        "source": "shelf_wishlist",
        "target": "4NQC4sGwaR5jiqhGiRRLtP",
        "type": "contains"
      },
      {
        "source": "shelf_wishlist",
        "target": "4fr1rDv2291dAVKPtcMRgP",
        "type": "contains"
      },
      {
        "source": "shelf_wishlist",
        "target": "5MRX5FqPV4gQJ4SUJEGR6y",
        "type": "contains"
      },
      {
        "source": "shelf_wishlist",
        "target": "18pFJWDeqhqBh48Sxwnw63",
        "type": "contains"
      },
      {
        "source": "shelf_complete",
        "target": "3ErINWu9y8qqJzA3uSJxaK",
        "type": "contains"
      },
      {
        "source": "shelf_complete",
        "target": "1GJZfHPBtJf3ekmbeA90Ts",
        "type": "contains"
      },
      {
        "source": "shelf_complete",
        "target": "1MQTe6StK7U9anZfXwrvxN",
        "type": "contains"
      },
      {
        "source": "shelf_complete",
        "target": "5SfUpBL7Ep6RIIa7TQBmtT",
        "type": "contains"
      },
      {
        "source": "shelf_complete",
        "target": "6SypDUBDZDeKkHSHfWRILc",
        "type": "contains"
      },
      {
        "source": "shelf_complete",
        "target": "59TkmZ7Evnn4xGWSY7fkgo",
        "type": "contains"
      },
      {
        "source": "shelf_complete",
        "target": "5ZQLUcgq9hI0ZRq4DnJ9Nw",
        "type": "contains"
      },
      {
        "source": "shelf_complete",
        "target": "7SReOVIEq3itRypnDbcRqE",
        "type": "contains"
      },
      {
        "source": "shelf_complete",
        "target": "6O7xHFAeXj8lmvsUJhpsIm",
        "type": "contains"
      },
      {
        "source": "shelf_complete",
        "target": "3aUNnyrU6XNSjKp3mHIUGy",
        "type": "contains"
      },
      {
        "source": "shelf_complete",
        "target": "0rlhTdTgCiMzTsk6Nzc1qO",
        "type": "contains"
      },
      {
        "source": "shelf_complete",
        "target": "61VXoCBbwZmEPMpek3dPv5",
        "type": "contains"
      },
      {
        "source": "shelf_complete",
        "target": "7W8mWPRsHRbscXIKDwaDNt",
        "type": "contains"
      },
      {
        "source": "shelf_complete",
        "target": "0CcoCzEy5UsdunAqMezUK1",
        "type": "contains"
      },
      {
        "source": "shelf_complete",
        "target": "1tx0NXYNYw1B1EbzEOH8Ut",
        "type": "contains"
      },
      {
        "source": "shelf_complete",
        "target": "50UegkSltjhfK9xvcVRPfJ",
        "type": "contains"
      },
      {
        "source": "shelf_complete",
        "target": "73OfKaiBtVf3Z2zTl2UVlH",
        "type": "contains"
      },
      {
        "source": "shelf_complete",
        "target": "4S7NSuBKA3bpAjDbxXmxr3",
        "type": "contains"
      },
      {
        "source": "shelf_complete",
        "target": "0vkg5uKj3fNYCREftjzvi2",
        "type": "contains"
      },
      {
        "source": "shelf_complete",
        "target": "59HnjEbpyVtxmZT3pfNaOm",
        "type": "contains"
      }
    ]
  }
}